<?xml version="1.0" encoding="utf-8"?>
<WebResource xmlns:xsi="http://www.w3.org/2001/XMLSchema-instance">
  <WebResourceId>{1c16a1a2-52ca-f011-bbd3-6045bd0a5843}</WebResourceId>
  <Name>wsf_ribbon.js</Name>
  <DisplayName>Script Botões - Barra de Comando</DisplayName>
  <Description>Biblioteca JavaScript centralizada para ações da Barra de Comandos (Ribbon) na tabela de Requisições. Contém funções para transição de status via WebAPI (Aprovar, Rejeitar, Pedido Realizado, Concluir), garantindo a execução e atualização de tela mesmo quando o formulário está bloqueado para edição.</Description>
  <LanguageCode>0</LanguageCode>
  <WebResourceType>3</WebResourceType>
  <IntroducedVersion>1.0.0.0</IntroducedVersion>
  <IsEnabledForMobileClient>0</IsEnabledForMobileClient>
  <IsAvailableForMobileOffline>0</IsAvailableForMobileOffline>
  <IsCustomizable>1</IsCustomizable>
  <CanBeDeleted>1</CanBeDeleted>
  <IsHidden>0</IsHidden>
  <FileName>/WebResources/wsf_ribbonjs1C16A1A2-52CA-F011-BBD3-6045BD0A5843</FileName>
</WebResource>